main.py
ldst_monitor/__init__.py
ldst_monitor/ding.py
ldst_monitor/main.py
ldst_monitor/monitor.py
ldst_monitor-1.0.7.dist-info/METADATA
ldst_monitor-1.0.7.dist-info/WHEEL
ldst_monitor-1.0.7.dist-info/top_level.txt
ldst_monitor-1.0.7.dist-info/RECORD
