Metadata-Version: 2.1
Name: ldst-monitor
Version: 1.0.7
Summary: A small example package
Author-email: Happy <author@example.com>
Classifier: Programming Language :: Python :: 3
Classifier: License :: OSI Approved :: MIT License
Classifier: Operating System :: OS Independent
Requires-Python: >=3.7
Requires-Dist: requests
Requires-Dist: python-dotenv
